aiosql_mysql/__init__.py
aiosql_mysql/utilities.py
aiosql_mysql/adapters/__init__.py
aiosql_mysql/adapters/asyncmy.py
aiosql_mysql/adapters/pymysql.py
tests/__init__.py
tests/asyncmy_fixture.py
tests/docker_fixture.py
tests/pymysql_fixture.py
tests/test_asyncmy.py
tests/test_pymysql.py
tests/test_utilities.py
aiosql_mysql-0.0.1a1.dist-info/LICENSE
aiosql_mysql-0.0.1a1.dist-info/METADATA
aiosql_mysql-0.0.1a1.dist-info/WHEEL
aiosql_mysql-0.0.1a1.dist-info/top_level.txt
aiosql_mysql-0.0.1a1.dist-info/RECORD
