Metadata-Version: 2.1
Name: aiosql-mysql
Version: 0.0.1a1
Summary: A MySQL driver adaptor for aiosql
Home-page: https://github.com/kajuberdut/aiosql-mysql
Author: Patrick Shechet
Author-email: patrick.shechet@gmail.com
License: MIT
Platform: UNKNOWN
Classifier: Development Status :: 3 - Alpha
Classifier: Programming Language :: Python :: 3 :: Only
License-File: LICENSE
Provides-Extra: asyncmy
Requires-Dist: asyncmy ; extra == 'asyncmy'
Provides-Extra: pymysql
Requires-Dist: pymysql[rsa] ; extra == 'pymysql'
